beancount_periodic/__init__.py
beancount_periodic/amortize.py
beancount_periodic/depreciate.py
beancount_periodic/recur.py
beancount_periodic/split.py
beancount_periodic/common/__init__.py
beancount_periodic/common/config.py
beancount_periodic/common/config_test.py
beancount_periodic/common/number.py
beancount_periodic/common/number_test.py
beancount_periodic/common/plugin_utils.py
beancount_periodic/common/utils.py
beancount_periodic-0.2.1.dist-info/licenses/LICENSE
beancount_periodic-0.2.1.dist-info/METADATA
beancount_periodic-0.2.1.dist-info/WHEEL
beancount_periodic-0.2.1.dist-info/top_level.txt
beancount_periodic-0.2.1.dist-info/RECORD
