Metadata-Version: 2.4
Name: beancount-periodic
Version: 0.2.1
Summary: Beancount plugin to generate periodic transactions #Amortize #Depreciate #Recur
Home-page: https://github.com/dallaslu/beancount-periodic
Author: Dallas Lu
Author-email: 914202+dallaslu@users.noreply.github.com
Project-URL: Issue tracker, https://github.com/dallaslu/beancount-periodic/issues
Classifier: Programming Language :: Python :: 3
Classifier: Operating System :: OS Independent
Classifier: Topic :: Office/Business :: Financial :: Accounting
Requires-Python: >=3.6
License-File: LICENSE
Requires-Dist: beancount>=2.3.4
Requires-Dist: beangulp>=0.1.1
Requires-Dist: python-dateutil~=2.9.0
Dynamic: author
Dynamic: author-email
Dynamic: classifier
Dynamic: description
Dynamic: description-content-type
Dynamic: home-page
Dynamic: license-file
Dynamic: project-url
Dynamic: requires-dist
Dynamic: requires-python
Dynamic: summary
